{
  "project_info": {
    "project_number": "321874139966",
    "project_id": "syrus-hackathon-p1-wmbglw",
    "storage_bucket": "syrus-hackathon-p1-wmbglw.appspot.com"
  },
  "client": [
    {
      "client_info": {
        "mobilesdk_app_id": "1:321874139966:android:014695ebb17442ce6c2a6f",
        "android_client_info": {
          "package_name": "com.mycompany.syrushackathonp1"
        }
      },
      "oauth_client": [],
      "api_key": [
        {
          "current_key": "AIzaSyDi5Z4NrpgG5rDQ3EjtZmIVz91yiq8QBqw"
        }
      ],
      "services": {
        "appinvite_service": {
          "other_platform_oauth_client": []
        }
      }
    }
  ],
  "configuration_version": "1"
}